nanome_rmsd/GreenCheck.png
nanome_rmsd/Lock.png
nanome_rmsd/None.png
nanome_rmsd/QuestionMark.png
nanome_rmsd/RMSD.py
nanome_rmsd/Refresh.png
nanome_rmsd/Ring.png
nanome_rmsd/Unlock.png
nanome_rmsd/__init__.py
nanome_rmsd/rmsd_calculation.py
nanome_rmsd/rmsd_helpers.py
nanome_rmsd/rmsd_menu.json
nanome_rmsd/rmsd_menu.py
nanome_rmsd/rmsd_pluginator.json
nanome_rmsd/rmsd_selection.py
nanome_rmsd-1.0.1.dist-info/LICENSE
nanome_rmsd-1.0.1.dist-info/METADATA
nanome_rmsd-1.0.1.dist-info/WHEEL
nanome_rmsd-1.0.1.dist-info/entry_points.txt
nanome_rmsd-1.0.1.dist-info/top_level.txt
nanome_rmsd-1.0.1.dist-info/RECORD
